fastapi_featureflags/__init__.py
fastapi_featureflags/main.py
fastapi_featureflags/router.py
fastapi_featureflags-0.4.9.dist-info/LICENSE
fastapi_featureflags-0.4.9.dist-info/METADATA
fastapi_featureflags-0.4.9.dist-info/WHEEL
fastapi_featureflags-0.4.9.dist-info/RECORD
