Metadata-Version: 2.1
Name: fastapi-featureflags
Version: 0.4.9
Summary: Feature Flags for FastAPI
Author: Tomas Pytel
Author-email: pytlicek@gmail.com
Requires-Python: >=3.8,<=3.12
Classifier: License :: OSI Approved :: MIT License
Classifier: Operating System :: OS Independent
Classifier: Programming Language :: Python :: 3
Classifier: Programming Language :: Python :: 3.8
Classifier: Programming Language :: Python :: 3.9
Classifier: Programming Language :: Python :: 3.10
Classifier: Programming Language :: Python :: 3.11
Classifier: Programming Language :: Python :: 3.12
Requires-Dist: fastapi (>=0.103.1,<0.104.0)
Requires-Dist: requests (>=2.29.0,<3.0.0)
Project-URL: Homepage, https://github.com/Pytlicek/fastapi-featureflags
